play_dv_on_windows/__init__.py
play_dv_on_windows/cli.py
play_dv_on_windows/config_manager.py
play_dv_on_windows/convert.py
play_dv_on_windows/qbt_post_process.py
play_dv_on_windows/config/default.json
play_dv_on_windows/config/local.json
play_dv_on_windows-1.0.13.dist-info/licenses/LICENSE
play_dv_on_windows-1.0.13.dist-info/METADATA
play_dv_on_windows-1.0.13.dist-info/WHEEL
play_dv_on_windows-1.0.13.dist-info/entry_points.txt
play_dv_on_windows-1.0.13.dist-info/top_level.txt
play_dv_on_windows-1.0.13.dist-info/RECORD
