Metadata-Version: 2.4
Name: play-dv-on-windows
Version: 1.0.13
Summary: A comprehensive 4K Dolby Vision MKV to MP4 converter with qBittorrent integration
Author-email: anfen <anfen93@gmail.com>
License: MIT
Project-URL: Homepage, https://github.com/anfen93/play-dv-on-windows
Project-URL: Repository, https://github.com/anfen93/play-dv-on-windows
Project-URL: Documentation, https://github.com/anfen93/play-dv-on-windows/docs
Project-URL: Issues, https://github.com/anfen93/play-dv-on-windows/issues
Keywords: dolby-vision,mkv,mp4,converter,qbittorrent,4k
Classifier: Development Status :: 5 - Production/Stable
Classifier: Intended Audience :: End Users/Desktop
Classifier: License :: OSI Approved :: MIT License
Classifier: Operating System :: OS Independent
Classifier: Programming Language :: Python :: 3
Classifier: Programming Language :: Python :: 3.8
Classifier: Programming Language :: Python :: 3.9
Classifier: Programming Language :: Python :: 3.10
Classifier: Programming Language :: Python :: 3.11
Classifier: Programming Language :: Python :: 3.12
Classifier: Topic :: Multimedia :: Video :: Conversion
Requires-Python: >=3.8
License-File: LICENSE
Requires-Dist: psutil>=5.8.0
Requires-Dist: requests>=2.31.0
Provides-Extra: dev
Requires-Dist: pytest>=6.0.0; extra == "dev"
Requires-Dist: pytest-cov>=2.0.0; extra == "dev"
Requires-Dist: black>=21.0.0; extra == "dev"
Requires-Dist: flake8>=3.8.0; extra == "dev"
Dynamic: license-file
